GrassGisZhongwenJiaocheng/README.md
GrassGisZhongwenJiaocheng/__init__.py
GrassGisZhongwenJiaocheng/__main__.py
GrassGisZhongwenJiaocheng/file.epub
GrassGisZhongwenJiaocheng/index.html
GrassGisZhongwenJiaocheng/css/__init__.py
GrassGisZhongwenJiaocheng/css/annotations.css
GrassGisZhongwenJiaocheng/css/main.css
GrassGisZhongwenJiaocheng/css/normalize.css
GrassGisZhongwenJiaocheng/css/popup.css
GrassGisZhongwenJiaocheng/font/__init__.py
GrassGisZhongwenJiaocheng/font/fontello.eot
GrassGisZhongwenJiaocheng/font/fontello.svg
GrassGisZhongwenJiaocheng/font/fontello.ttf
GrassGisZhongwenJiaocheng/font/fontello.woff
GrassGisZhongwenJiaocheng/img/__init__.py
GrassGisZhongwenJiaocheng/img/annotator-glyph-sprite.png
GrassGisZhongwenJiaocheng/img/annotator-icon-sprite.png
GrassGisZhongwenJiaocheng/img/apple-touch-icon.png
GrassGisZhongwenJiaocheng/img/cancelfullscreen.png
GrassGisZhongwenJiaocheng/img/close.png
GrassGisZhongwenJiaocheng/img/fullscreen.png
GrassGisZhongwenJiaocheng/img/loader.gif
GrassGisZhongwenJiaocheng/img/menu-icon.png
GrassGisZhongwenJiaocheng/img/save.png
GrassGisZhongwenJiaocheng/img/saved.png
GrassGisZhongwenJiaocheng/img/settings-s.png
GrassGisZhongwenJiaocheng/img/settings.png
GrassGisZhongwenJiaocheng/img/star.png
GrassGisZhongwenJiaocheng/js/__init__.py
GrassGisZhongwenJiaocheng/js/epub.js
GrassGisZhongwenJiaocheng/js/epub.min.js
GrassGisZhongwenJiaocheng/js/epub.min.map
GrassGisZhongwenJiaocheng/js/hooks.min.js
GrassGisZhongwenJiaocheng/js/hooks.min.map
GrassGisZhongwenJiaocheng/js/reader.js
GrassGisZhongwenJiaocheng/js/reader.js.map
GrassGisZhongwenJiaocheng/js/reader.min.js
GrassGisZhongwenJiaocheng/js/reader.min.map
GrassGisZhongwenJiaocheng/js/hooks/__init__.py
GrassGisZhongwenJiaocheng/js/hooks/extensions/__init__.py
GrassGisZhongwenJiaocheng/js/hooks/extensions/highlight.js
GrassGisZhongwenJiaocheng/js/libs/__init__.py
GrassGisZhongwenJiaocheng/js/libs/jquery.min.js
GrassGisZhongwenJiaocheng/js/libs/localforage.min.js
grass_gis_zhongwen_jiaocheng-2024.3.5.0.dist-info/METADATA
grass_gis_zhongwen_jiaocheng-2024.3.5.0.dist-info/WHEEL
grass_gis_zhongwen_jiaocheng-2024.3.5.0.dist-info/entry_points.txt
grass_gis_zhongwen_jiaocheng-2024.3.5.0.dist-info/top_level.txt
grass_gis_zhongwen_jiaocheng-2024.3.5.0.dist-info/RECORD
